darksky.py
darkskypy-0.3.1.dist-info/DESCRIPTION.rst
darkskypy-0.3.1.dist-info/METADATA
darkskypy-0.3.1.dist-info/RECORD
darkskypy-0.3.1.dist-info/WHEEL
darkskypy-0.3.1.dist-info/metadata.json
darkskypy-0.3.1.dist-info/top_level.txt
