Metadata-Version: 2.0
Name: darkskypy
Version: 0.3.1
Summary: A different python wrapper to access weather data provided by DarkSky.net
Home-page: https://github.com/mattbox/DarkSkyPy
Author: mattbox
Author-email: mattbox@noreply.github.com
License: MIT
Platform: UNKNOWN
Requires-Dist: attrdict
Requires-Dist: requests
